pybadges2/__init__.py
pybadges2/__main__.py
pybadges2/badge-template-full.svg
pybadges2/badge.py
pybadges2/default-widths.json
pybadges2/detect_image_type.py
pybadges2/embed_image.py
pybadges2/pil_text_measurer.py
pybadges2/precalculate_text.py
pybadges2/precalculated_text_measurer.py
pybadges2/text_measurer.py
pybadges2/util.py
pybadges2/version.py
pybadges2-2024.11.23.dist-info/entry_points.txt
pybadges2-2024.11.23.dist-info/LICENSE
pybadges2-2024.11.23.dist-info/WHEEL
pybadges2-2024.11.23.dist-info/METADATA
pybadges2-2024.11.23.dist-info/RECORD
