Metadata-Version: 2.3
Name: pybadges2
Version: 2024.11.23
Summary: Library and command-line tool for generating GitHub-style badges
Keywords: badge,gh-badges,github,shield,status
Author-email: Brian Quinlan <brian@sweetapp.com>
Maintainer-email: James Knight <git@jdknight.me>
Requires-Python: >=3.9
Classifier: Development Status :: 5 - Production/Stable
Classifier: Intended Audience :: Developers
Classifier: License :: OSI Approved :: Apache Software License
Classifier: License :: OSI Approved :: BSD License
Classifier: Operating System :: OS Independent
Classifier: Programming Language :: Python :: 3 :: Only
Classifier: Programming Language :: Python :: 3
Classifier: Programming Language :: Python :: 3.9
Classifier: Programming Language :: Python :: 3.10
Classifier: Programming Language :: Python :: 3.11
Classifier: Programming Language :: Python :: 3.12
Classifier: Programming Language :: Python :: 3.13
Classifier: Programming Language :: Python
Requires-Dist: Jinja2
Requires-Dist: requests
Project-URL: Download, https://pypi.python.org/pypi/pybadges2
Project-URL: Source, https://github.com/jdknight/pybadges2
